README.md
setup.cfg
setup.py
tensor2tensor/__init__.py
tensor2tensor/problems.py
tensor2tensor/problems_test.py
tensor2tensor/bin/__init__.py
tensor2tensor/bin/build_vocab.py
tensor2tensor/bin/make_tf_configs.py
tensor2tensor/bin/t2t-avg-all
tensor2tensor/bin/t2t-bleu
tensor2tensor/bin/t2t-datagen
tensor2tensor/bin/t2t-decoder
tensor2tensor/bin/t2t-eval
tensor2tensor/bin/t2t-exporter
tensor2tensor/bin/t2t-insights-server
tensor2tensor/bin/t2t-make-tf-configs
tensor2tensor/bin/t2t-query-server
tensor2tensor/bin/t2t-trainer
tensor2tensor/bin/t2t-translate-all
tensor2tensor/bin/t2t_attack.py
tensor2tensor/bin/t2t_avg_all.py
tensor2tensor/bin/t2t_bleu.py
tensor2tensor/bin/t2t_datagen.py
tensor2tensor/bin/t2t_decoder.py
tensor2tensor/bin/t2t_distill.py
tensor2tensor/bin/t2t_eval.py
tensor2tensor/bin/t2t_prune.py
tensor2tensor/bin/t2t_trainer.py
tensor2tensor/bin/t2t_trainer_test.py
tensor2tensor/bin/t2t_translate_all.py
tensor2tensor/data_generators/__init__.py
tensor2tensor/data_generators/algorithmic.py
tensor2tensor/data_generators/algorithmic_math.py
tensor2tensor/data_generators/algorithmic_math_test.py
tensor2tensor/data_generators/algorithmic_math_two_variables.py
tensor2tensor/data_generators/algorithmic_test.py
tensor2tensor/data_generators/all_problems.py
tensor2tensor/data_generators/allen_brain.py
tensor2tensor/data_generators/allen_brain_test.py
tensor2tensor/data_generators/audio.py
tensor2tensor/data_generators/audio_encoder.py
tensor2tensor/data_generators/audio_test.py
tensor2tensor/data_generators/babi_qa.py
tensor2tensor/data_generators/bair_robot_pushing.py
tensor2tensor/data_generators/celeba.py
tensor2tensor/data_generators/celeba_test.py
tensor2tensor/data_generators/celebahq.py
tensor2tensor/data_generators/cifar.py
tensor2tensor/data_generators/cipher.py
tensor2tensor/data_generators/cleaner_en_xx.py
tensor2tensor/data_generators/cnn_dailymail.py
tensor2tensor/data_generators/cola.py
tensor2tensor/data_generators/common_voice.py
tensor2tensorM.egg-info/PKG-INFO
tensor2tensorM.egg-info/SOURCES.txt
tensor2tensorM.egg-info/dependency_links.txt
tensor2tensorM.egg-info/requires.txt
tensor2tensorM.egg-info/top_level.txt