Metadata-Version: 2.1
Name: tensor2tensorM
Version: 2.0.9
Summary: Tensor2TensorM
Home-page: https://github.com/manuel3265/tensor
Author: Manuel Garcia
Author-email: manuel.garcia02@uptc.edu.co
License: Apache 2.0
Keywords: tensorflow machine learning
Platform: UNKNOWN
Classifier: Development Status :: 4 - Beta
Classifier: Intended Audience :: Developers
Classifier: Intended Audience :: Science/Research
Classifier: License :: OSI Approved :: Apache Software License
Classifier: Topic :: Scientific/Engineering :: Artificial Intelligence
Provides-Extra: allen
Provides-Extra: tensorflow
Provides-Extra: tensorflow-hub
Provides-Extra: tensorflow_gpu
Provides-Extra: tests
